esdm/__init__.py
esdm/__main__.py
esdm-1.6.dist-info/METADATA
esdm-1.6.dist-info/WHEEL
esdm-1.6.dist-info/entry_points.txt
esdm-1.6.dist-info/top_level.txt
esdm-1.6.dist-info/RECORD
