Metadata-Version: 2.1
Name: esdm
Version: 1.6
Summary: A easy SSH device manger
